sancal/__init__.py
sancal-0.1.dist-info/LICENCE.txt.txt
sancal-0.1.dist-info/METADATA
sancal-0.1.dist-info/WHEEL
sancal-0.1.dist-info/top_level.txt
sancal-0.1.dist-info/RECORD
