Metadata-Version: 2.1
Name: sancal
Version: 0.1
Summary: Basic desc
Home-page: UNKNOWN
Author: skg31st
Author-email: skg31st@gmail.com
License: UNKNOWN
Platform: UNKNOWN
Classifier: Programming Language :: Python :: 3
Classifier: License :: OSI Approved :: MIT License
Classifier: Operating System :: OS Independent
